[{"id":1,"playerName":"Patrice Bergeron","playerNumber":37,"color":"Away","size":"XL","price":249.99,"quantity":3,"avgReview":0.0,"reviews":[],"imagePath":"https://cdn11.bigcommerce.com/s-b0wguna27q/images/stencil/960w/products/4567/10855/PatriceBergeronBlueLine2011StanleyCupFInalJersey1000__88766.1696024292.jpg?c=2"},{"id":2,"playerName":"Terry O'Reilly","playerNumber":24,"color":"Away","size":"XS","price":10.99,"quantity":63,"avgReview":0.0,"reviews":[],"imagePath":"https://cdn11.bigcommerce.com/s-b0wguna27q/images/stencil/1320x1320/products/4471/10615/OReillyFanaticsBreakawayJersey1000__34033.1695481944.jpg?c=2"},{"id":3,"playerName":"Charlie McAvoy","playerNumber":73,"color":"Home","size":"S","price":110.99,"quantity":1,"avgReview":5.0,"reviews":[["Really Hungry Mouse","5","It tastes so good"],["John","5","its okay"]],"imagePath":"https://cdn11.bigcommerce.com/s-b0wguna27q/images/stencil/960w/products/4410/10454/McAvoyLadiesCentennialFanaticsBreakawayHomeJersey1000__83997.1698949810.jpg?c=2"},{"id":4,"playerName":"Charlie Coyle","playerNumber":13,"color":"Away","size":"M","price":112.99,"quantity":14,"avgReview":4.0,"reviews":[["Guy341","5","Its so cool"],["BruinsH8ter","3","I dont like the bruins why did I buy this, feels nice tho."]],"imagePath":"https://cdn11.bigcommerce.com/s-b0wguna27q/images/stencil/960w/products/3159/11266/CoyleThirdJersey1000__97536.1697478679.jpg?c=2"},{"id":5,"playerName":"Jeremy Swayman","playerNumber":1,"color":"Home","size":"L","price":244.99,"quantity":3,"avgReview":5.0,"reviews":[["Jeremy Swayman's Mom","5","I LOVE MY SON"]],"imagePath":"https://cdn11.bigcommerce.com/s-b0wguna27q/images/stencil/960w/products/3118/7301/SwaymanPrimegreenHomeJersey1000__31517.1686746887.jpg?c=2"},{"id":6,"playerName":"Basic T-Shirt","playerNumber":1,"color":"Flexible","size":"M","price":19.99,"quantity":18,"avgReview":3.5,"reviews":[["admin","5","testing"],["test","3","hi"],["john","1","hi"],["john","5","hi"],["john","5","hi"],["john","3","bye"]],"imagePath":"assets/media/jersey.png"},{"id":7,"playerName":"David Krejčí","playerNumber":46,"color":"Away","size":"XXL","price":149.99,"quantity":9,"avgReview":5.0,"reviews":[["alex","5","hi"]],"imagePath":"https://cdn11.bigcommerce.com/s-b0wguna27q/images/stencil/960w/products/3519/8285/KrejciPrimegreenHomeJersey1000__34914.1659987512.jpg?c=2"},{"id":8,"playerName":"Brad Marchand","playerNumber":63,"color":"Home","size":"L","price":199.99,"quantity":0,"avgReview":0.0,"reviews":[],"imagePath":"https://cdn11.bigcommerce.com/s-b0wguna27q/images/stencil/960w/products/4400/10420/MarchandYouthCentennialThirdJersey1000__89745.1694814073.jpg?c=2"}]